Workbook

Sheet Summary Dashboard
A1: ABC Store — Expense Tracker 2026 | Summary Dashboard
A2: Prepared by: Farhan Siddique | Virtual Assistant & Data Specialist | May 2026
A4: KEY PERFORMANCE INDICATORS
A5: YTD Budget | B5: YTD Actual | C5: Total Variance | D5: Avg Monthly | E5: Over Budget | F5: Savings Rate
A6: =SUM(C12:C17) | B6: =SUM(D12:D17) | C6: =D6-C6 | D6: =C6/6 | E6: =COUNTIF(F12:F17,"Over Budget") | F6: =IF(C6>0,(C6-D6)/C6,0)
A11: Month | B11: Days | C11: Budget ($) | D11: Actual ($) | E11: Variance ($) | F11: Status | G11: % Used | H11: Notes
A12: January | B12: 31 | C12: 3500 | D12: ='Jan 2026'!P3 | E12: =D12-C12 | F12: =IF(D12>C12,"Over Budget","On Track") | G12: =IF(C12>0,D12/C12,0)
A13: February | B13: 28 | C13: 3200 | D13: ='Feb 2026'!P3 | E13: =D13-C13 | F13: =IF(D13>C13,"Over Budget","On Track") | G13: =IF(C13>0,D13/C13,0)
A14: March | B14: 31 | C14: 3300 | D14: ='Mar 2026'!P3 | E14: =D14-C14 | F14: =IF(D14>C14,"Over Budget","On Track") | G14: =IF(C14>0,D14/C14,0)
A15: April | B15: 30 | C15: 3500 | D15: ='Apr 2026'!P3 | E15: =D15-C15 | F15: =IF(D15>C15,"Over Budget","On Track") | G15: =IF(C15>0,D15/C15,0)
A16: May | B16: 31 | C16: 3500 | D16: ='May 2026'!P3 | E16: =D16-C16 | F16: =IF(D16>C16,"Over Budget","On Track") | G16: =IF(C16>0,D16/C16,0)
A17: June | B17: 30 | C17: 3600 | D17: ='Jun 2026'!P3 | E17: =D17-C17 | F17: =IF(D17>C17,"Over Budget","On Track") | G17: =IF(C17>0,D17/C17,0)
A18: YTD TOTAL | C18: =SUM(C12:C17) | D18: =SUM(D12:D17) | E18: =SUM(E12:E17)

Sheet Jan 2026
A1: ABC Store — January 2026 Detailed Expenses
A2: Farhan Siddique | Virtual Assistant & Data Specialist | May 2026
P3: =SUM(E8:E25)
A4: Month Budget | B4: Total Spent | C4: Remaining | D4: # Transactions | E4: Avg Transaction
A5: 3500 | B5: =SUM(E8:E60) | C5: =A5-B5 | D5: =COUNTA(A8:A60) | E5: =IF(D5>0,B5/D5,0)
A7: Date | B7: Category | C7: Description | D7: Payment Method | E7: Amount ($) | F7: Notes | G7: Cumulative ($)
A8: 01-Jan-26 | B8: Rent | C8: Office rent – January | D8: Bank Transfer | E8: 1200 | F8: Monthly fixed | G8: =SUM($E$8:E8)
A9: 02-Jan-26 | B9: Utilities | C9: Electricity bill | D9: Bank Transfer | E9: 195.5 | G9: =SUM($E$8:E9)
A10: 03-Jan-26 | B10: Supplies | C10: Printer paper & toner (bulk) | D10: Cash | E10: 89.8 | G10: =SUM($E$8:E10)
A11: 05-Jan-26 | B11: Internet | C11: Broadband – January | D11: Auto Debit | E11: 49.99 | G11: =SUM($E$8:E11)
A12: 06-Jan-26 | B12: Marketing | C12: Google Ads campaign | D12: Credit Card | E12: 200 | F12: Campaign #08 | G12: =SUM($E$8:E12)
A13: 07-Jan-26 | B13: Salaries | C13: Part-time staff wage | D13: Bank Transfer | E13: 600 | F13: 2 staff × 4 days | G13: =SUM($E$8:E13)
A14: 10-Jan-26 | B14: Equipment | C14: External hard drive backup | D14: Cash | E14: 59.99 | G14: =SUM($E$8:E14)
A15: 12-Jan-26 | B15: Supplies | C15: Cleaning supplies | D15: Cash | E15: 22.4 | G15: =SUM($E$8:E15)
A16: 14-Jan-26 | B16: Transport | C16: Delivery – supplier pickup | D16: Cash | E16: 18 | G16: =SUM($E$8:E16)
A17: 15-Jan-26 | B17: Marketing | C17: Instagram boost | D17: Credit Card | E17: 50 | G17: =SUM($E$8:E17)
A18: 18-Jan-26 | B18: Utilities | C18: Water bill | D18: Bank Transfer | E18: 38 | G18: =SUM($E$8:E18)
A19: 20-Jan-26 | B19: Supplies | C19: Stationery restock | D19: Cash | E19: 31.2 | G19: =SUM($E$8:E19)
A20: 22-Jan-26 | B20: Maintenance | C20: HVAC filter replacement | D20: Cash | E20: 45 | G20: =SUM($E$8:E20)
A21: 25-Jan-26 | B21: Transport | C21: Courier delivery charges | D21: Cash | E21: 28.5 | G21: =SUM($E$8:E21)
A22: 28-Jan-26 | B22: Miscellaneous | C22: Staff refreshments | D22: Cash | E22: 33.12 | G22: =SUM($E$8:E22)
A23: 29-Jan-26 | B23: Insurance | C23: Business liability premium | D23: Bank Transfer | E23: 150 | F23: Monthly | G23: =SUM($E$8:E23)
A24: 30-Jan-26 | B24: Software | C24: Accounting software license | D24: Credit Card | E24: 29.99 | G24: =SUM($E$8:E24)
A25: 31-Jan-26 | B25: Supplies | C25: Packaging materials | D25: Cash | E25: 66 | F25: Bulk order | G25: =SUM($E$8:E25)
C26: MONTH TOTAL | E26: =SUM(E8:E25)

Sheet Feb 2026
A1: ABC Store — February 2026 Detailed Expenses
A2: Farhan Siddique | Virtual Assistant & Data Specialist | May 2026
P3: =SUM(E8:E25)
A4: Month Budget | B4: Total Spent | C4: Remaining | D4: # Transactions | E4: Avg Transaction
A5: 3200 | B5: =SUM(E8:E60) | C5: =A5-B5 | D5: =COUNTA(A8:A60) | E5: =IF(D5>0,B5/D5,0)
A7: Date | B7: Category | C7: Description | D7: Payment Method | E7: Amount ($) | F7: Notes | G7: Cumulative ($)
A8: 01-Feb-26 | B8: Rent | C8: Office rent – February | D8: Bank Transfer | E8: 1200 | F8: Monthly fixed | G8: =SUM($E$8:E8)
A9: 02-Feb-26 | B9: Utilities | C9: Electricity bill | D9: Bank Transfer | E9: 182 | G9: =SUM($E$8:E9)
A10: 03-Feb-26 | B10: Supplies | C10: Printer paper – restock | D10: Cash | E10: 44 | G10: =SUM($E$8:E10)
A11: 05-Feb-26 | B11: Internet | C11: Broadband – February | D11: Auto Debit | E11: 49.99 | G11: =SUM($E$8:E11)
A12: 07-Feb-26 | B12: Marketing | C12: Facebook Ads | D12: Credit Card | E12: 175 | F12: Valentine campaign | G12: =SUM($E$8:E12)
A13: 08-Feb-26 | B13: Salaries | C13: Part-time staff wage | D13: Bank Transfer | E13: 600 | G13: =SUM($E$8:E13)
A14: 10-Feb-26 | B14: Equipment | C14: Label printer ribbons | D14: Cash | E14: 24.99 | G14: =SUM($E$8:E14)
A15: 12-Feb-26 | B15: Supplies | C15: Cleaning supplies | D15: Cash | E15: 19.8 | G15: =SUM($E$8:E15)
A16: 14-Feb-26 | B16: Transport | C16: Delivery – supplier pickup | D16: Cash | E16: 22 | G16: =SUM($E$8:E16)
A17: 15-Feb-26 | B17: Marketing | C17: Flyer printing | D17: Cash | E17: 85 | G17: =SUM($E$8:E17)
A18: 18-Feb-26 | B18: Utilities | C18: Water bill | D18: Bank Transfer | E18: 41 | G18: =SUM($E$8:E18)
A19: 20-Feb-26 | B19: Supplies | C19: Stationery restock | D19: Cash | E19: 28.5 | G19: =SUM($E$8:E19)
A20: 21-Feb-26 | B20: Maintenance | C20: Plumbing repair | D20: Cash | E20: 120 | F20: Unexpected | G20: =SUM($E$8:E20)
A21: 25-Feb-26 | B21: Transport | C21: Courier charges | D21: Cash | E21: 19 | G21: =SUM($E$8:E21)
A22: 27-Feb-26 | B22: Miscellaneous | C22: Office party supplies | D22: Cash | E22: 55 | G22: =SUM($E$8:E22)
A23: 28-Feb-26 | B23: Insurance | C23: Business liability premium | D23: Bank Transfer | E23: 150 | F23: Monthly | G23: =SUM($E$8:E23)
A24: 28-Feb-26 | B24: Software | C24: Cloud storage subscription | D24: Credit Card | E24: 14.99 | G24: =SUM($E$8:E24)
A25: 28-Feb-26 | B25: Supplies | C25: Packaging materials | D25: Cash | E25: 54 | G25: =SUM($E$8:E25)
C26: MONTH TOTAL | E26: =SUM(E8:E25)

Sheet Mar 2026
A1: ABC Store — March 2026 Detailed Expenses
A2: Farhan Siddique | Virtual Assistant & Data Specialist | May 2026
P3: =SUM(E8:E25)
A4: Month Budget | B4: Total Spent | C4: Remaining | D4: # Transactions | E4: Avg Transaction
A5: 3300 | B5: =SUM(E8:E60) | C5: =A5-B5 | D5: =COUNTA(A8:A60) | E5: =IF(D5>0,B5/D5,0)
A7: Date | B7: Category | C7: Description | D7: Payment Method | E7: Amount ($) | F7: Notes | G7: Cumulative ($)
A8: 01-Mar-26 | B8: Rent | C8: Office rent – March | D8: Bank Transfer | E8: 1200 | F8: Monthly fixed | G8: =SUM($E$8:E8)
A9: 02-Mar-26 | B9: Utilities | C9: Electricity bill | D9: Bank Transfer | E9: 168.4 | G9: =SUM($E$8:E9)
A10: 03-Mar-26 | B10: Supplies | C10: Printer paper & cartridges | D10: Cash | E10: 78.2 | G10: =SUM($E$8:E10)
A11: 05-Mar-26 | B11: Internet | C11: Broadband – March | D11: Auto Debit | E11: 49.99 | G11: =SUM($E$8:E11)
A12: 07-Mar-26 | B12: Marketing | C12: Google Ads | D12: Credit Card | E12: 220 | F12: Spring campaign | G12: =SUM($E$8:E12)
A13: 08-Mar-26 | B13: Salaries | C13: Part-time staff wage | D13: Bank Transfer | E13: 600 | G13: =SUM($E$8:E13)
A14: 10-Mar-26 | B14: Equipment | C14: Surge protector strips | D14: Cash | E14: 39.98 | F14: 2 units | G14: =SUM($E$8:E14)
A15: 12-Mar-26 | B15: Supplies | C15: Cleaning supplies | D15: Cash | E15: 21.6 | G15: =SUM($E$8:E15)
A16: 14-Mar-26 | B16: Transport | C16: Delivery – supplier pickup | D16: Cash | E16: 15 | G16: =SUM($E$8:E16)
A17: 15-Mar-26 | B17: Marketing | C17: Social media management tool | D17: Credit Card | E17: 49 | F17: Monthly | G17: =SUM($E$8:E17)
A18: 18-Mar-26 | B18: Utilities | C18: Water bill | D18: Bank Transfer | E18: 36 | G18: =SUM($E$8:E18)
A19: 20-Mar-26 | B19: Supplies | C19: Stationery restock | D19: Cash | E19: 33.8 | G19: =SUM($E$8:E19)
A20: 22-Mar-26 | B20: Maintenance | C20: AC filter change | D20: Cash | E20: 60 | G20: =SUM($E$8:E20)
A21: 25-Mar-26 | B21: Transport | C21: Courier charges | D21: Cash | E21: 21 | G21: =SUM($E$8:E21)
A22: 28-Mar-26 | B22: Miscellaneous | C22: Client meeting refreshments | D22: Cash | E22: 38 | G22: =SUM($E$8:E22)
A23: 29-Mar-26 | B23: Insurance | C23: Business liability premium | D23: Bank Transfer | E23: 150 | F23: Monthly | G23: =SUM($E$8:E23)
A24: 30-Mar-26 | B24: Software | C24: Project management tool | D24: Credit Card | E24: 25 | G24: =SUM($E$8:E24)
A25: 31-Mar-26 | B25: Supplies | C25: Packaging materials – Q1 bulk | D25: Cash | E25: 70 | G25: =SUM($E$8:E25)
C26: MONTH TOTAL | E26: =SUM(E8:E25)

Sheet Apr 2026
A1: ABC Store — April 2026 Detailed Expenses
A2: Farhan Siddique | Virtual Assistant & Data Specialist | May 2026
P3: =SUM(E8:E25)
A4: Month Budget | B4: Total Spent | C4: Remaining | D4: # Transactions | E4: Avg Transaction
A5: 3500 | B5: =SUM(E8:E60) | C5: =A5-B5 | D5: =COUNTA(A8:A60) | E5: =IF(D5>0,B5/D5,0)
A7: Date | B7: Category | C7: Description | D7: Payment Method | E7: Amount ($) | F7: Notes | G7: Cumulative ($)
A8: 01-Apr-26 | B8: Rent | C8: Office rent – April | D8: Bank Transfer | E8: 1200 | F8: Monthly fixed | G8: =SUM($E$8:E8)
A9: 02-Apr-26 | B9: Utilities | C9: Electricity bill | D9: Bank Transfer | E9: 210.8 | F9: Warmer weather | G9: =SUM($E$8:E9)
A10: 03-Apr-26 | B10: Supplies | C10: Printer paper | D10: Cash | E10: 44 | G10: =SUM($E$8:E10)
A11: 05-Apr-26 | B11: Internet | C11: Broadband – April | D11: Auto Debit | E11: 49.99 | G11: =SUM($E$8:E11)
A12: 07-Apr-26 | B12: Marketing | C12: Facebook + Google Ads | D12: Credit Card | E12: 300 | F12: Easter promotion | G12: =SUM($E$8:E12)
A13: 08-Apr-26 | B13: Salaries | C13: Part-time staff wage | D13: Bank Transfer | E13: 600 | G13: =SUM($E$8:E13)
A14: 10-Apr-26 | B14: Equipment | C14: Wireless keyboard replacement | D14: Cash | E14: 49.99 | G14: =SUM($E$8:E14)
A15: 12-Apr-26 | B15: Supplies | C15: Cleaning supplies | D15: Cash | E15: 23 | G15: =SUM($E$8:E15)
A16: 14-Apr-26 | B16: Transport | C16: Delivery – supplier pickup | D16: Cash | E16: 25 | F16: Larger order | G16: =SUM($E$8:E16)
A17: 15-Apr-26 | B17: Marketing | C17: Email marketing platform | D17: Credit Card | E17: 29 | G17: =SUM($E$8:E17)
A18: 18-Apr-26 | B18: Utilities | C18: Water bill | D18: Bank Transfer | E18: 39 | G18: =SUM($E$8:E18)
A19: 20-Apr-26 | B19: Supplies | C19: Stationery restock | D19: Cash | E19: 29.8 | G19: =SUM($E$8:E19)
A20: 22-Apr-26 | B20: Maintenance | C20: Office door lock repair | D20: Cash | E20: 85 | F20: Security | G20: =SUM($E$8:E20)
A21: 25-Apr-26 | B21: Transport | C21: Courier charges | D21: Cash | E21: 18 | G21: =SUM($E$8:E21)
A22: 28-Apr-26 | B22: Miscellaneous | C22: Staff outing contribution | D22: Cash | E22: 80 | F22: Team morale | G22: =SUM($E$8:E22)
A23: 29-Apr-26 | B23: Insurance | C23: Business liability premium | D23: Bank Transfer | E23: 150 | F23: Monthly | G23: =SUM($E$8:E23)
A24: 30-Apr-26 | B24: Software | C24: Accounting software | D24: Credit Card | E24: 29.99 | G24: =SUM($E$8:E24)
A25: 30-Apr-26 | B25: Supplies | C25: Packaging materials | D25: Cash | E25: 61 | G25: =SUM($E$8:E25)
C26: MONTH TOTAL | E26: =SUM(E8:E25)

Sheet May 2026
A1: ABC Store — May 2026 Detailed Expenses
A2: Farhan Siddique | Virtual Assistant & Data Specialist | May 2026
P3: =SUM(E8:E25)
A4: Month Budget | B4: Total Spent | C4: Remaining | D4: # Transactions | E4: Avg Transaction
A5: 3500 | B5: =SUM(E8:E60) | C5: =A5-B5 | D5: =COUNTA(A8:A60) | E5: =IF(D5>0,B5/D5,0)
A7: Date | B7: Category | C7: Description | D7: Payment Method | E7: Amount ($) | F7: Notes | G7: Cumulative ($)
A8: 01-May-26 | B8: Rent | C8: Office rent – May | D8: Bank Transfer | E8: 1200 | F8: Monthly fixed | G8: =SUM($E$8:E8)
A9: 02-May-26 | B9: Utilities | C9: Electricity bill | D9: Bank Transfer | E9: 185.5 | G9: =SUM($E$8:E9)
A10: 03-May-26 | B10: Supplies | C10: Printer paper & toner | D10: Cash | E10: 67.8 | G10: =SUM($E$8:E10)
A11: 05-May-26 | B11: Internet | C11: Broadband – May | D11: Auto Debit | E11: 49.99 | G11: =SUM($E$8:E11)
A12: 07-May-26 | B12: Marketing | C12: Facebook Ads | D12: Credit Card | E12: 150 | F12: Campaign #12 | G12: =SUM($E$8:E12)
A13: 08-May-26 | B13: Salaries | C13: Part-time staff wage | D13: Bank Transfer | E13: 600 | F13: 2 staff x 4 days | G13: =SUM($E$8:E13)
A14: 10-May-26 | B14: Equipment | C14: USB hub for counter PC | D14: Cash | E14: 34.99 | G14: =SUM($E$8:E14)
A15: 12-May-26 | B15: Supplies | C15: Cleaning supplies | D15: Cash | E15: 22.4 | G15: =SUM($E$8:E15)
A16: 14-May-26 | B16: Transport | C16: Delivery – supplier pickup | D16: Cash | E16: 18 | G16: =SUM($E$8:E16)
A17: 15-May-26 | B17: Marketing | C17: Instagram boost post | D17: Credit Card | E17: 50 | G17: =SUM($E$8:E17)
A18: 18-May-26 | B18: Utilities | C18: Water bill | D18: Bank Transfer | E18: 42 | G18: =SUM($E$8:E18)
A19: 20-May-26 | B19: Supplies | C19: Stationery restock | D19: Cash | E19: 31.2 | G19: =SUM($E$8:E19)
A20: 22-May-26 | B20: Maintenance | C20: AC servicing | D20: Cash | E20: 80 | F20: Annual service | G20: =SUM($E$8:E20)
A21: 25-May-26 | B21: Transport | C21: Delivery fuel | D21: Cash | E21: 15 | G21: =SUM($E$8:E21)
A22: 28-May-26 | B22: Miscellaneous | C22: Staff refreshments | D22: Cash | E22: 33.12 | G22: =SUM($E$8:E22)
A23: 29-May-26 | B23: Insurance | C23: Business liability premium | D23: Bank Transfer | E23: 150 | F23: Monthly | G23: =SUM($E$8:E23)
A24: 30-May-26 | B24: Software | C24: Accounting software license | D24: Credit Card | E24: 29.99 | G24: =SUM($E$8:E24)
A25: 31-May-26 | B25: Supplies | C25: Packaging materials | D25: Cash | E25: 67 | G25: =SUM($E$8:E25)
C26: MONTH TOTAL | E26: =SUM(E8:E25)

Sheet Jun 2026
A1: ABC Store — June 2026 Detailed Expenses
A2: Farhan Siddique | Virtual Assistant & Data Specialist | May 2026
P3: =SUM(E8:E25)
A4: Month Budget | B4: Total Spent | C4: Remaining | D4: # Transactions | E4: Avg Transaction
A5: 3600 | B5: =SUM(E8:E60) | C5: =A5-B5 | D5: =COUNTA(A8:A60) | E5: =IF(D5>0,B5/D5,0)
A7: Date | B7: Category | C7: Description | D7: Payment Method | E7: Amount ($) | F7: Notes | G7: Cumulative ($)
A8: 01-Jun-26 | B8: Rent | C8: Office rent – June | D8: Bank Transfer | E8: 1200 | F8: Monthly fixed | G8: =SUM($E$8:E8)
A9: 02-Jun-26 | B9: Utilities | C9: Electricity bill | D9: Bank Transfer | E9: 225.6 | F9: Summer peak | G9: =SUM($E$8:E9)
A10: 03-Jun-26 | B10: Supplies | C10: Printer paper & toner | D10: Cash | E10: 72 | G10: =SUM($E$8:E10)
A11: 05-Jun-26 | B11: Internet | C11: Broadband – June | D11: Auto Debit | E11: 49.99 | G11: =SUM($E$8:E11)
A12: 07-Jun-26 | B12: Marketing | C12: Mid-year sale campaign | D12: Credit Card | E12: 280 | F12: Google + FB | G12: =SUM($E$8:E12)
A13: 08-Jun-26 | B13: Salaries | C13: Part-time staff wage | D13: Bank Transfer | E13: 600 | G13: =SUM($E$8:E13)
A14: 10-Jun-26 | B14: Equipment | C14: Monitor cleaning kit | D14: Cash | E14: 19.99 | G14: =SUM($E$8:E14)
A15: 12-Jun-26 | B15: Supplies | C15: Cleaning supplies | D15: Cash | E15: 24 | G15: =SUM($E$8:E15)
A16: 14-Jun-26 | B16: Transport | C16: Delivery – supplier pickup | D16: Cash | E16: 22 | G16: =SUM($E$8:E16)
A17: 15-Jun-26 | B17: Marketing | C17: Influencer promotion | D17: Credit Card | E17: 150 | F17: Micro-influencer | G17: =SUM($E$8:E17)
A18: 18-Jun-26 | B18: Utilities | C18: Water bill | D18: Bank Transfer | E18: 44 | G18: =SUM($E$8:E18)
A19: 20-Jun-26 | B19: Supplies | C19: Stationery restock | D19: Cash | E19: 35 | G19: =SUM($E$8:E19)
A20: 22-Jun-26 | B20: Maintenance | C20: Pest control service | D20: Cash | E20: 90 | F20: Quarterly | G20: =SUM($E$8:E20)
A21: 25-Jun-26 | B21: Transport | C21: Courier charges | D21: Cash | E21: 27 | G21: =SUM($E$8:E21)
A22: 28-Jun-26 | B22: Miscellaneous | C22: Mid-year staff lunch | D22: Cash | E22: 120 | F22: 12 staff | G22: =SUM($E$8:E22)
A23: 29-Jun-26 | B23: Insurance | C23: Business liability premium | D23: Bank Transfer | E23: 150 | F23: Monthly | G23: =SUM($E$8:E23)
A24: 30-Jun-26 | B24: Software | C24: All subscriptions – June | D24: Credit Card | E24: 68.98 | G24: =SUM($E$8:E24)
A25: 30-Jun-26 | B25: Supplies | C25: Packaging materials | D25: Cash | E25: 74 | G25: =SUM($E$8:E25)
C26: MONTH TOTAL | E26: =SUM(E8:E25)

Sheet Category Breakdown
A1: ABC Store — Category Breakdown by Month 2026
A2: Farhan Siddique | Virtual Assistant & Data Specialist | May 2026
A4: Category | B4: Jan | C4: Feb | D4: Mar | E4: Apr | F4: May | G4: Jun | H4: YTD Total | I4: % of Total
A5: Rent | B5: 1200 | C5: 1200 | D5: 1200 | E5: 1200 | F5: 1200 | G5: 1200 | H5: =SUM(B5:G5) | I5: =IF(SUM($H$5:$H$16)>0,H5/SUM($H$5:$H$16),0)
A6: Utilities | B6: 233.5 | C6: 223 | D6: 204.4 | E6: 249.8 | F6: 227.5 | G6: 269.6 | H6: =SUM(B6:G6) | I6: =IF(SUM($H$5:$H$16)>0,H6/SUM($H$5:$H$16),0)
A7: Supplies | B7: 209.4 | C7: 146.3 | D7: 203.6 | E7: 157.8 | F7: 188.4 | G7: 205 | H7: =SUM(B7:G7) | I7: =IF(SUM($H$5:$H$16)>0,H7/SUM($H$5:$H$16),0)
A8: Internet | B8: 49.99 | C8: 49.99 | D8: 49.99 | E8: 49.99 | F8: 49.99 | G8: 49.99 | H8: =SUM(B8:G8) | I8: =IF(SUM($H$5:$H$16)>0,H8/SUM($H$5:$H$16),0)
A9: Marketing | B9: 250 | C9: 260 | D9: 269 | E9: 329 | F9: 200 | G9: 430 | H9: =SUM(B9:G9) | I9: =IF(SUM($H$5:$H$16)>0,H9/SUM($H$5:$H$16),0)
A10: Salaries | B10: 600 | C10: 600 | D10: 600 | E10: 600 | F10: 600 | G10: 600 | H10: =SUM(B10:G10) | I10: =IF(SUM($H$5:$H$16)>0,H10/SUM($H$5:$H$16),0)
A11: Equipment | B11: 59.99 | C11: 24.99 | D11: 39.98 | E11: 49.99 | F11: 34.99 | G11: 19.99 | H11: =SUM(B11:G11) | I11: =IF(SUM($H$5:$H$16)>0,H11/SUM($H$5:$H$16),0)
A12: Transport | B12: 46.5 | C12: 41 | D12: 36 | E12: 43 | F12: 33 | G12: 49 | H12: =SUM(B12:G12) | I12: =IF(SUM($H$5:$H$16)>0,H12/SUM($H$5:$H$16),0)
A13: Maintenance | B13: 45 | C13: 120 | D13: 60 | E13: 85 | F13: 80 | G13: 90 | H13: =SUM(B13:G13) | I13: =IF(SUM($H$5:$H$16)>0,H13/SUM($H$5:$H$16),0)
A14: Miscellaneous | B14: 33.12 | C14: 55 | D14: 38 | E14: 80 | F14: 33.12 | G14: 120 | H14: =SUM(B14:G14) | I14: =IF(SUM($H$5:$H$16)>0,H14/SUM($H$5:$H$16),0)
A15: Insurance | B15: 150 | C15: 150 | D15: 150 | E15: 150 | F15: 150 | G15: 150 | H15: =SUM(B15:G15) | I15: =IF(SUM($H$5:$H$16)>0,H15/SUM($H$5:$H$16),0)
A16: Software | B16: 29.99 | C16: 14.99 | D16: 25 | E16: 29.99 | F16: 29.99 | G16: 68.98 | H16: =SUM(B16:G16) | I16: =IF(SUM($H$5:$H$16)>0,H16/SUM($H$5:$H$16),0)
A17: TOTAL | B17: =SUM(B5:B16) | C17: =SUM(C5:C16) | D17: =SUM(D5:D16) | E17: =SUM(E5:E16) | F17: =SUM(F5:F16) | G17: =SUM(G5:G16) | H17: =SUM(H5:H16) | I17: 100.0%

Sheet YTD Analysis
A1: ABC Store — Year-to-Date Analysis 2026
A2: Farhan Siddique | Virtual Assistant & Data Specialist | May 2026
A4: BUDGET vs ACTUAL VARIANCE ANALYSIS
A5: Month | B5: Budget | C5: Actual | D5: Variance | E5: Var % | F5: Trend vs Prior
A6: January | B6: 3500 | C6: 2907.49 | D6: =C6-B6 | E6: =IF(B6>0,(C6-B6)/B6,0) | F6: Baseline
A7: February | B7: 3200 | C7: 2885.27 | D7: =C7-B7 | E7: =IF(B7>0,(C7-B7)/B7,0) | F7: =IF(C7>C6,"Higher","Lower")
A8: March | B8: 3300 | C8: 2875.97 | D8: =C8-B8 | E8: =IF(B8>0,(C8-B8)/B8,0) | F8: =IF(C8>C7,"Higher","Lower")
A9: April | B9: 3500 | C9: 3024.57 | D9: =C9-B9 | E9: =IF(B9>0,(C9-B9)/B9,0) | F9: =IF(C9>C8,"Higher","Lower")
A10: May | B10: 3500 | C10: 2826.99 | D10: =C10-B10 | E10: =IF(B10>0,(C10-B10)/B10,0) | F10: =IF(C10>C9,"Higher","Lower")
A11: June | B11: 3600 | C11: 3252.56 | D11: =C11-B11 | E11: =IF(B11>0,(C11-B11)/B11,0) | F11: =IF(C11>C10,"Higher","Lower")
A12: YTD TOTAL | B12: =SUM(B6:B11) | C12: =SUM(C6:C11) | D12: =SUM(D6:D11) | E12: =AVERAGE(E6:E11)
A14: TREND ANALYSIS — Monthly Spend Pattern
A15: Month | B15: Actual Spend | C15: MoM Change ($) | D15: MoM Change (%) | E15: 3-Mo Avg | F15: Status
A16: January | B16: 2907.49 | C16: — | D16: — | E16: 2907.49 | F16: Baseline
A17: February | B17: 2885.27 | C17: =B17-B16 | D17: =IF(B16<>0,(B17-B16)/B16,0) | E17: =AVERAGE(B16:B17) | F17: =IF(B17>AVERAGE($B$16:$B$21),"Above Avg","Below Avg")
A18: March | B18: 2875.97 | C18: =B18-B17 | D18: =IF(B17<>0,(B18-B17)/B17,0) | E18: =AVERAGE(B16:B18) | F18: =IF(B18>AVERAGE($B$16:$B$21),"Above Avg","Below Avg")
A19: April | B19: 3024.57 | C19: =B19-B18 | D19: =IF(B18<>0,(B19-B18)/B18,0) | E19: =AVERAGE(B17:B19) | F19: =IF(B19>AVERAGE($B$16:$B$21),"Above Avg","Below Avg")
A20: May | B20: 2826.99 | C20: =B20-B19 | D20: =IF(B19<>0,(B20-B19)/B19,0) | E20: =AVERAGE(B18:B20) | F20: =IF(B20>AVERAGE($B$16:$B$21),"Above Avg","Below Avg")
A21: June | B21: 3252.56 | C21: =B21-B20 | D21: =IF(B20<>0,(B21-B20)/B20,0) | E21: =AVERAGE(B19:B21) | F21: =IF(B21>AVERAGE($B$16:$B$21),"Above Avg","Below Avg")
