Workbook

Sheet 📊 Budget Dashboard
A1: 💰 MONTHLY BUDGET DASHBOARD | 2026
A2: Small Business Finance | Revenue • Expenses • Profit • Budget vs Actual | Auto-updates from Budget Data & Budget Targets sheets
A3: Prepared by Farhan Siddique | Digital Marketer & Data Analyst | HubSpot, Google & Microsoft Certified
B4: TOTAL ANNUAL REVENUE | F4: TOTAL ANNUAL EXPENSES | J4: NET PROFIT / LOSS
B5: ='💰 Budget Data'!O17 | F5: ='💰 Budget Data'!O18 | J5: ='💰 Budget Data'!O19
A8: MONTHLY REVENUE vs EXPENSES vs NET PROFIT
B9: Month | C9: Budgeted Rev | D9: Actual Rev | E9: Rev Variance | F9: Rev % | G9: Actual Exp | H9: Budget Exp | I9: Exp Variance | J9: Exp % | K9: Net Profit | L9: Prev Month | M9: MoM Change
B10: Jan | C10: ='🎯 Budget Targets'!C4+'🎯 Budget Targets'!C5+'🎯 Budget Targets'!C6 | D10: ='💰 Budget Data'!C17 | E10: =D10-C10 | F10: =IFERROR((D10-C10)/C10,0) | G10: ='💰 Budget Data'!C18 | H10: ='🎯 Budget Targets'!C8+'🎯 Budget Targets'!C9+'🎯 Budget Targets'!C10+'🎯 Budget Targets'!C11+'🎯 Budget Targets'!C12+'🎯 Budget Targets'!C13+'🎯 Budget Targets'!C14+'🎯 Budget Targets'!C15+'🎯 Budget Targets'!C16 | I10: =H10-G10 | J10: =IFERROR((H10-G10)/H10,0) | K10: ='💰 Budget Data'!C19 | L10: 0 | M10: =IFERROR((K10-L10)/ABS(L10),0)
B11: Feb | C11: ='🎯 Budget Targets'!D4+'🎯 Budget Targets'!D5+'🎯 Budget Targets'!D6 | D11: ='💰 Budget Data'!D17 | E11: =D11-C11 | F11: =IFERROR((D11-C11)/C11,0) | G11: ='💰 Budget Data'!D18 | H11: ='🎯 Budget Targets'!D8+'🎯 Budget Targets'!D9+'🎯 Budget Targets'!D10+'🎯 Budget Targets'!D11+'🎯 Budget Targets'!D12+'🎯 Budget Targets'!D13+'🎯 Budget Targets'!D14+'🎯 Budget Targets'!D15+'🎯 Budget Targets'!D16 | I11: =H11-G11 | J11: =IFERROR((H11-G11)/H11,0) | K11: ='💰 Budget Data'!D19 | L11: =K10 | M11: =IFERROR((K11-L11)/ABS(L11),0)
B12: Mar | C12: ='🎯 Budget Targets'!E4+'🎯 Budget Targets'!E5+'🎯 Budget Targets'!E6 | D12: ='💰 Budget Data'!E17 | E12: =D12-C12 | F12: =IFERROR((D12-C12)/C12,0) | G12: ='💰 Budget Data'!E18 | H12: ='🎯 Budget Targets'!E8+'🎯 Budget Targets'!E9+'🎯 Budget Targets'!E10+'🎯 Budget Targets'!E11+'🎯 Budget Targets'!E12+'🎯 Budget Targets'!E13+'🎯 Budget Targets'!E14+'🎯 Budget Targets'!E15+'🎯 Budget Targets'!E16 | I12: =H12-G12 | J12: =IFERROR((H12-G12)/H12,0) | K12: ='💰 Budget Data'!E19 | L12: =K11 | M12: =IFERROR((K12-L12)/ABS(L12),0)
B13: Apr | C13: ='🎯 Budget Targets'!F4+'🎯 Budget Targets'!F5+'🎯 Budget Targets'!F6 | D13: ='💰 Budget Data'!F17 | E13: =D13-C13 | F13: =IFERROR((D13-C13)/C13,0) | G13: ='💰 Budget Data'!F18 | H13: ='🎯 Budget Targets'!F8+'🎯 Budget Targets'!F9+'🎯 Budget Targets'!F10+'🎯 Budget Targets'!F11+'🎯 Budget Targets'!F12+'🎯 Budget Targets'!F13+'🎯 Budget Targets'!F14+'🎯 Budget Targets'!F15+'🎯 Budget Targets'!F16 | I13: =H13-G13 | J13: =IFERROR((H13-G13)/H13,0) | K13: ='💰 Budget Data'!F19 | L13: =K12 | M13: =IFERROR((K13-L13)/ABS(L13),0)
B14: May | C14: ='🎯 Budget Targets'!G4+'🎯 Budget Targets'!G5+'🎯 Budget Targets'!G6 | D14: ='💰 Budget Data'!G17 | E14: =D14-C14 | F14: =IFERROR((D14-C14)/C14,0) | G14: ='💰 Budget Data'!G18 | H14: ='🎯 Budget Targets'!G8+'🎯 Budget Targets'!G9+'🎯 Budget Targets'!G10+'🎯 Budget Targets'!G11+'🎯 Budget Targets'!G12+'🎯 Budget Targets'!G13+'🎯 Budget Targets'!G14+'🎯 Budget Targets'!G15+'🎯 Budget Targets'!G16 | I14: =H14-G14 | J14: =IFERROR((H14-G14)/H14,0) | K14: ='💰 Budget Data'!G19 | L14: =K13 | M14: =IFERROR((K14-L14)/ABS(L14),0)
B15: Jun | C15: ='🎯 Budget Targets'!H4+'🎯 Budget Targets'!H5+'🎯 Budget Targets'!H6 | D15: ='💰 Budget Data'!H17 | E15: =D15-C15 | F15: =IFERROR((D15-C15)/C15,0) | G15: ='💰 Budget Data'!H18 | H15: ='🎯 Budget Targets'!H8+'🎯 Budget Targets'!H9+'🎯 Budget Targets'!H10+'🎯 Budget Targets'!H11+'🎯 Budget Targets'!H12+'🎯 Budget Targets'!H13+'🎯 Budget Targets'!H14+'🎯 Budget Targets'!H15+'🎯 Budget Targets'!H16 | I15: =H15-G15 | J15: =IFERROR((H15-G15)/H15,0) | K15: ='💰 Budget Data'!H19 | L15: =K14 | M15: =IFERROR((K15-L15)/ABS(L15),0)
B16: Jul | C16: ='🎯 Budget Targets'!I4+'🎯 Budget Targets'!I5+'🎯 Budget Targets'!I6 | D16: ='💰 Budget Data'!I17 | E16: =D16-C16 | F16: =IFERROR((D16-C16)/C16,0) | G16: ='💰 Budget Data'!I18 | H16: ='🎯 Budget Targets'!I8+'🎯 Budget Targets'!I9+'🎯 Budget Targets'!I10+'🎯 Budget Targets'!I11+'🎯 Budget Targets'!I12+'🎯 Budget Targets'!I13+'🎯 Budget Targets'!I14+'🎯 Budget Targets'!I15+'🎯 Budget Targets'!I16 | I16: =H16-G16 | J16: =IFERROR((H16-G16)/H16,0) | K16: ='💰 Budget Data'!I19 | L16: =K15 | M16: =IFERROR((K16-L16)/ABS(L16),0)
B17: Aug | C17: ='🎯 Budget Targets'!J4+'🎯 Budget Targets'!J5+'🎯 Budget Targets'!J6 | D17: ='💰 Budget Data'!J17 | E17: =D17-C17 | F17: =IFERROR((D17-C17)/C17,0) | G17: ='💰 Budget Data'!J18 | H17: ='🎯 Budget Targets'!J8+'🎯 Budget Targets'!J9+'🎯 Budget Targets'!J10+'🎯 Budget Targets'!J11+'🎯 Budget Targets'!J12+'🎯 Budget Targets'!J13+'🎯 Budget Targets'!J14+'🎯 Budget Targets'!J15+'🎯 Budget Targets'!J16 | I17: =H17-G17 | J17: =IFERROR((H17-G17)/H17,0) | K17: ='💰 Budget Data'!J19 | L17: =K16 | M17: =IFERROR((K17-L17)/ABS(L17),0)
B18: Sep | C18: ='🎯 Budget Targets'!K4+'🎯 Budget Targets'!K5+'🎯 Budget Targets'!K6 | D18: ='💰 Budget Data'!K17 | E18: =D18-C18 | F18: =IFERROR((D18-C18)/C18,0) | G18: ='💰 Budget Data'!K18 | H18: ='🎯 Budget Targets'!K8+'🎯 Budget Targets'!K9+'🎯 Budget Targets'!K10+'🎯 Budget Targets'!K11+'🎯 Budget Targets'!K12+'🎯 Budget Targets'!K13+'🎯 Budget Targets'!K14+'🎯 Budget Targets'!K15+'🎯 Budget Targets'!K16 | I18: =H18-G18 | J18: =IFERROR((H18-G18)/H18,0) | K18: ='💰 Budget Data'!K19 | L18: =K17 | M18: =IFERROR((K18-L18)/ABS(L18),0)
B19: Oct | C19: ='🎯 Budget Targets'!L4+'🎯 Budget Targets'!L5+'🎯 Budget Targets'!L6 | D19: ='💰 Budget Data'!L17 | E19: =D19-C19 | F19: =IFERROR((D19-C19)/C19,0) | G19: ='💰 Budget Data'!L18 | H19: ='🎯 Budget Targets'!L8+'🎯 Budget Targets'!L9+'🎯 Budget Targets'!L10+'🎯 Budget Targets'!L11+'🎯 Budget Targets'!L12+'🎯 Budget Targets'!L13+'🎯 Budget Targets'!L14+'🎯 Budget Targets'!L15+'🎯 Budget Targets'!L16 | I19: =H19-G19 | J19: =IFERROR((H19-G19)/H19,0) | K19: ='💰 Budget Data'!L19 | L19: =K18 | M19: =IFERROR((K19-L19)/ABS(L19),0)
B20: Nov | C20: ='🎯 Budget Targets'!M4+'🎯 Budget Targets'!M5+'🎯 Budget Targets'!M6 | D20: ='💰 Budget Data'!M17 | E20: =D20-C20 | F20: =IFERROR((D20-C20)/C20,0) | G20: ='💰 Budget Data'!M18 | H20: ='🎯 Budget Targets'!M8+'🎯 Budget Targets'!M9+'🎯 Budget Targets'!M10+'🎯 Budget Targets'!M11+'🎯 Budget Targets'!M12+'🎯 Budget Targets'!M13+'🎯 Budget Targets'!M14+'🎯 Budget Targets'!M15+'🎯 Budget Targets'!M16 | I20: =H20-G20 | J20: =IFERROR((H20-G20)/H20,0) | K20: ='💰 Budget Data'!M19 | L20: =K19 | M20: =IFERROR((K20-L20)/ABS(L20),0)
B21: Dec | C21: ='🎯 Budget Targets'!N4+'🎯 Budget Targets'!N5+'🎯 Budget Targets'!N6 | D21: ='💰 Budget Data'!N17 | E21: =D21-C21 | F21: =IFERROR((D21-C21)/C21,0) | G21: ='💰 Budget Data'!N18 | H21: ='🎯 Budget Targets'!N8+'🎯 Budget Targets'!N9+'🎯 Budget Targets'!N10+'🎯 Budget Targets'!N11+'🎯 Budget Targets'!N12+'🎯 Budget Targets'!N13+'🎯 Budget Targets'!N14+'🎯 Budget Targets'!N15+'🎯 Budget Targets'!N16 | I21: =H21-G21 | J21: =IFERROR((H21-G21)/H21,0) | K21: ='💰 Budget Data'!N19 | L21: =K20 | M21: =IFERROR((K21-L21)/ABS(L21),0)
B22: ANNUAL TOTAL | C22: =SUM(C10:C21) | D22: =SUM(D10:D21) | E22: =SUM(E10:E21) | F22: =IFERROR(E22/C22,0) | G22: =SUM(G10:G21) | H22: =SUM(H10:H21) | I22: =SUM(I10:I21) | J22: =IFERROR(I22/H22,0) | K22: =SUM(K10:K21)
A24: ANNUAL EXPENSE BREAKDOWN | Category Analysis
B25: Category | C25: Annual Budget | D25: Annual Actual | E25: Variance ($) | F25: Variance (%) | G25: Q1 Actual | H25: Q2 Actual | I25: Q3 Actual | J25: Q4 Actual | K25: Avg Monthly | L25: Max Month | M25: Status
B26: Salaries & Wages | C26: =SUM('🎯 Budget Targets'!C9:N9) | D26: ='💰 Budget Data'!O8 | E26: =D26-C26 | F26: =IFERROR(E26/C26,0) | G26: =SUM('💰 Budget Data'!C8:E8) | H26: =SUM('💰 Budget Data'!F8:H8) | I26: =SUM('💰 Budget Data'!I8:K8) | J26: =SUM('💰 Budget Data'!L8:N8) | K26: =IFERROR(D26/12,0) | L26: =IFERROR(MAX('💰 Budget Data'!C8:N8),0) | M26: =IF(E26<=0,"✅ Under Budget",IF(F26<0.1,"⚠️ Near Limit","❌ Over Budget"))
B27: Rent & Utilities | C27: =SUM('🎯 Budget Targets'!C10:N10) | D27: ='💰 Budget Data'!O9 | E27: =D27-C27 | F27: =IFERROR(E27/C27,0) | G27: =SUM('💰 Budget Data'!C9:E9) | H27: =SUM('💰 Budget Data'!F9:H9) | I27: =SUM('💰 Budget Data'!I9:K9) | J27: =SUM('💰 Budget Data'!L9:N9) | K27: =IFERROR(D27/12,0) | L27: =IFERROR(MAX('💰 Budget Data'!C9:N9),0) | M27: =IF(E27<=0,"✅ Under Budget",IF(F27<0.1,"⚠️ Near Limit","❌ Over Budget"))
B28: Marketing & Ads | C28: =SUM('🎯 Budget Targets'!C11:N11) | D28: ='💰 Budget Data'!O10 | E28: =D28-C28 | F28: =IFERROR(E28/C28,0) | G28: =SUM('💰 Budget Data'!C10:E10) | H28: =SUM('💰 Budget Data'!F10:H10) | I28: =SUM('💰 Budget Data'!I10:K10) | J28: =SUM('💰 Budget Data'!L10:N10) | K28: =IFERROR(D28/12,0) | L28: =IFERROR(MAX('💰 Budget Data'!C10:N10),0) | M28: =IF(E28<=0,"✅ Under Budget",IF(F28<0.1,"⚠️ Near Limit","❌ Over Budget"))
B29: Software & Tools | C29: =SUM('🎯 Budget Targets'!C12:N12) | D29: ='💰 Budget Data'!O11 | E29: =D29-C29 | F29: =IFERROR(E29/C29,0) | G29: =SUM('💰 Budget Data'!C11:E11) | H29: =SUM('💰 Budget Data'!F11:H11) | I29: =SUM('💰 Budget Data'!I11:K11) | J29: =SUM('💰 Budget Data'!L11:N11) | K29: =IFERROR(D29/12,0) | L29: =IFERROR(MAX('💰 Budget Data'!C11:N11),0) | M29: =IF(E29<=0,"✅ Under Budget",IF(F29<0.1,"⚠️ Near Limit","❌ Over Budget"))
B30: Travel & Entertainment | C30: =SUM('🎯 Budget Targets'!C13:N13) | D30: ='💰 Budget Data'!O12 | E30: =D30-C30 | F30: =IFERROR(E30/C30,0) | G30: =SUM('💰 Budget Data'!C12:E12) | H30: =SUM('💰 Budget Data'!F12:H12) | I30: =SUM('💰 Budget Data'!I12:K12) | J30: =SUM('💰 Budget Data'!L12:N12) | K30: =IFERROR(D30/12,0) | L30: =IFERROR(MAX('💰 Budget Data'!C12:N12),0) | M30: =IF(E30<=0,"✅ Under Budget",IF(F30<0.1,"⚠️ Near Limit","❌ Over Budget"))
B31: Office Supplies | C31: =SUM('🎯 Budget Targets'!C14:N14) | D31: ='💰 Budget Data'!O13 | E31: =D31-C31 | F31: =IFERROR(E31/C31,0) | G31: =SUM('💰 Budget Data'!C13:E13) | H31: =SUM('💰 Budget Data'!F13:H13) | I31: =SUM('💰 Budget Data'!I13:K13) | J31: =SUM('💰 Budget Data'!L13:N13) | K31: =IFERROR(D31/12,0) | L31: =IFERROR(MAX('💰 Budget Data'!C13:N13),0) | M31: =IF(E31<=0,"✅ Under Budget",IF(F31<0.1,"⚠️ Near Limit","❌ Over Budget"))
B32: Professional Services | C32: =SUM('🎯 Budget Targets'!C15:N15) | D32: ='💰 Budget Data'!O14 | E32: =D32-C32 | F32: =IFERROR(E32/C32,0) | G32: =SUM('💰 Budget Data'!C14:E14) | H32: =SUM('💰 Budget Data'!F14:H14) | I32: =SUM('💰 Budget Data'!I14:K14) | J32: =SUM('💰 Budget Data'!L14:N14) | K32: =IFERROR(D32/12,0) | L32: =IFERROR(MAX('💰 Budget Data'!C14:N14),0) | M32: =IF(E32<=0,"✅ Under Budget",IF(F32<0.1,"⚠️ Near Limit","❌ Over Budget"))
B33: R&D / Training | C33: =SUM('🎯 Budget Targets'!C16:N16) | D33: ='💰 Budget Data'!O15 | E33: =D33-C33 | F33: =IFERROR(E33/C33,0) | G33: =SUM('💰 Budget Data'!C15:E15) | H33: =SUM('💰 Budget Data'!F15:H15) | I33: =SUM('💰 Budget Data'!I15:K15) | J33: =SUM('💰 Budget Data'!L15:N15) | K33: =IFERROR(D33/12,0) | L33: =IFERROR(MAX('💰 Budget Data'!C15:N15),0) | M33: =IF(E33<=0,"✅ Under Budget",IF(F33<0.1,"⚠️ Near Limit","❌ Over Budget"))
B34: Miscellaneous | C34: =SUM('🎯 Budget Targets'!C17:N17) | D34: ='💰 Budget Data'!O16 | E34: =D34-C34 | F34: =IFERROR(E34/C34,0) | G34: =SUM('💰 Budget Data'!C16:E16) | H34: =SUM('💰 Budget Data'!F16:H16) | I34: =SUM('💰 Budget Data'!I16:K16) | J34: =SUM('💰 Budget Data'!L16:N16) | K34: =IFERROR(D34/12,0) | L34: =IFERROR(MAX('💰 Budget Data'!C16:N16),0) | M34: =IF(E34<=0,"✅ Under Budget",IF(F34<0.1,"⚠️ Near Limit","❌ Over Budget"))

Sheet 💰 Budget Data
A1: MONTHLY BUDGET DATA | 2026 | Enter actual figures below
A2: Category | B2: Type | C2: Jan | D2: Feb | E2: Mar | F2: Apr | G2: May | H2: Jun | I2: Jul | J2: Aug | K2: Sep | L2: Oct | M2: Nov | N2: Dec | O2: Annual Total
A3: ── REVENUE ──
A4: Product Sales | B4: Revenue | C4: 82000 | D4: 75000 | E4: 90000 | F4: 95000 | G4: 88000 | H4: 102000 | I4: 98000 | J4: 85000 | K4: 91000 | L4: 110000 | M4: 105000 | N4: 120000 | O4: =SUM(C4:N4)
A5: Service Revenue | B5: Revenue | C5: 35000 | D5: 38000 | E5: 36000 | F5: 40000 | G5: 42000 | H5: 45000 | I5: 43000 | J5: 39000 | K5: 44000 | L5: 48000 | M5: 50000 | N5: 55000 | O5: =SUM(C5:N5)
A6: Other Income | B6: Revenue | C6: 5000 | D6: 3000 | E6: 4500 | F6: 6000 | G6: 5500 | H6: 7000 | I6: 4000 | J6: 3500 | K6: 6500 | L6: 8000 | M6: 5000 | N6: 9000 | O6: =SUM(C6:N6)
A7: ── EXPENSES ──
A8: Salaries & Wages | B8: Expenses | C8: 45000 | D8: 45000 | E8: 45000 | F8: 46000 | G8: 46000 | H8: 46000 | I8: 47000 | J8: 47000 | K8: 47000 | L8: 48000 | M8: 48000 | N8: 50000 | O8: =SUM(C8:N8)
A9: Rent & Utilities | B9: Expenses | C9: 8500 | D9: 8500 | E9: 8500 | F9: 8500 | G9: 8500 | H9: 8500 | I9: 8500 | J9: 8500 | K9: 8500 | L9: 8500 | M9: 8500 | N9: 8500 | O9: =SUM(C9:N9)
A10: Marketing & Ads | B10: Expenses | C10: 12000 | D10: 10000 | E10: 15000 | F10: 18000 | G10: 14000 | H10: 20000 | I10: 16000 | J10: 12000 | K10: 18000 | L10: 22000 | M10: 25000 | N10: 28000 | O10: =SUM(C10:N10)
A11: Software & Tools | B11: Expenses | C11: 3200 | D11: 3200 | E11: 3200 | F11: 3200 | G11: 3200 | H11: 3200 | I11: 3200 | J11: 3200 | K11: 3200 | L11: 3200 | M11: 3200 | N11: 3200 | O11: =SUM(C11:N11)
A12: Travel & Entertainment | B12: Expenses | C12: 2000 | D12: 1500 | E12: 3000 | F12: 2500 | G12: 4000 | H12: 5000 | I12: 3500 | J12: 2000 | K12: 4500 | L12: 3000 | M12: 2500 | N12: 3500 | O12: =SUM(C12:N12)
A13: Office Supplies | B13: Expenses | C13: 800 | D13: 600 | E13: 900 | F13: 750 | G13: 700 | H13: 850 | I13: 800 | J13: 650 | K13: 900 | L13: 1000 | M13: 750 | N13: 900 | O13: =SUM(C13:N13)
A14: Professional Services | B14: Expenses | C14: 5000 | D14: 5000 | E14: 5000 | F14: 5000 | G14: 5000 | H14: 5000 | I14: 5000 | J14: 5000 | K14: 5000 | L14: 5000 | M14: 5000 | N14: 5000 | O14: =SUM(C14:N14)
A15: R&D / Training | B15: Expenses | C15: 3000 | D15: 2500 | E15: 4000 | F15: 3500 | G15: 3000 | H15: 4500 | I15: 4000 | J15: 3000 | K15: 3500 | L15: 4000 | M15: 3500 | N15: 4000 | O15: =SUM(C15:N15)
A16: Miscellaneous | B16: Expenses | C16: 1200 | D16: 900 | E16: 1500 | F16: 1100 | G16: 1300 | H16: 1600 | I16: 1400 | J16: 1000 | K16: 1500 | L16: 1800 | M16: 1200 | N16: 2000 | O16: =SUM(C16:N16)
A17: TOTAL REVENUE | C17: =C4+C5+C6 | D17: =D4+D5+D6 | E17: =E4+E5+E6 | F17: =F4+F5+F6 | G17: =G4+G5+G6 | H17: =H4+H5+H6 | I17: =I4+I5+I6 | J17: =J4+J5+J6 | ... N17: =N4+N5+N6 | O17: =SUM(C17:N17)
A18: TOTAL EXPENSES | C18: =C8+C9+C10+C11+C12+C13+C14+C15+C16 | D18: =D8+D9+D10+D11+D12+D13+D14+D15+D16 | E18: =E8+E9+E10+E11+E12+E13+E14+E15+E16 | F18: =F8+F9+F10+F11+F12+F13+F14+F15+F16 | G18: =G8+G9+G10+G11+G12+G13+G14+G15+G16 | H18: =H8+H9+H10+H11+H12+H13+H14+H15+H16 | I18: =I8+I9+I10+I11+I12+I13+I14+I15+I16 | J18: =J8+J9+J10+J11+J12+J13+J14+J15+J16 | ... N18: =N8+N9+N10+N11+N12+N13+N14+N15+N16 | O18: =SUM(C18:N18)
A19: NET PROFIT / LOSS | C19: =C17-C18 | D19: =D17-D18 | E19: =E17-E18 | F19: =F17-F18 | G19: =G17-G18 | H19: =H17-H18 | I19: =I17-I18 | J19: =J17-J18 | ... O19: =O17-O18

Sheet 🎯 Budget Targets
A1: BUDGET TARGETS | 2026 | Set planned budgets here
A2: Category | B2: Type | C2: Jan | D2: Feb | E2: Mar | F2: Apr | G2: May | H2: Jun | I2: Jul | J2: Aug | K2: Sep | L2: Oct | M2: Nov | N2: Dec | O2: Annual Total
A3: ── REVENUE ──
A4: Product Sales | B4: Revenue | C4: 85000 | D4: 85000 | E4: 85000 | F4: 85000 | G4: 85000 | H4: 85000 | I4: 85000 | J4: 85000 | K4: 85000 | L4: 85000 | M4: 85000 | N4: 85000 | O4: =SUM(C4:N4)
A5: Service Revenue | B5: Revenue | C5: 37000 | D5: 37000 | E5: 37000 | F5: 37000 | G5: 37000 | H5: 37000 | I5: 37000 | J5: 37000 | K5: 37000 | L5: 37000 | M5: 37000 | N5: 37000 | O5: =SUM(C5:N5)
A6: Other Income | B6: Revenue | C6: 5000 | D6: 5000 | E6: 5000 | F6: 5000 | G6: 5000 | H6: 5000 | I6: 5000 | J6: 5000 | K6: 5000 | L6: 5000 | M6: 5000 | N6: 5000 | O6: =SUM(C6:N6)
A7: ── EXPENSES ──
A8: Salaries & Wages | B8: Expenses | C8: 46000 | D8: 46000 | E8: 46000 | F8: 46000 | G8: 46000 | H8: 46000 | I8: 46000 | J8: 46000 | K8: 46000 | L8: 46000 | M8: 46000 | N8: 46000 | O8: =SUM(C8:N8)
A9: Rent & Utilities | B9: Expenses | C9: 8500 | D9: 8500 | E9: 8500 | F9: 8500 | G9: 8500 | H9: 8500 | I9: 8500 | J9: 8500 | K9: 8500 | L9: 8500 | M9: 8500 | N9: 8500 | O9: =SUM(C9:N9)
A10: Marketing & Ads | B10: Expenses | C10: 15000 | D10: 12000 | E10: 16000 | F10: 20000 | G10: 15000 | H10: 22000 | I10: 18000 | J10: 13000 | K10: 20000 | L10: 24000 | M10: 27000 | N10: 30000 | O10: =SUM(C10:N10)
A11: Software & Tools | B11: Expenses | C11: 3200 | D11: 3200 | E11: 3200 | F11: 3200 | G11: 3200 | H11: 3200 | I11: 3200 | J11: 3200 | K11: 3200 | L11: 3200 | M11: 3200 | N11: 3200 | O11: =SUM(C11:N11)
A12: Travel & Entertainment | B12: Expenses | C12: 2500 | D12: 2500 | E12: 2500 | F12: 2500 | G12: 2500 | H12: 2500 | I12: 2500 | J12: 2500 | K12: 2500 | L12: 2500 | M12: 2500 | N12: 2500 | O12: =SUM(C12:N12)
A13: Office Supplies | B13: Expenses | C13: 1000 | D13: 1000 | E13: 1000 | F13: 1000 | G13: 1000 | H13: 1000 | I13: 1000 | J13: 1000 | K13: 1000 | L13: 1000 | M13: 1000 | N13: 1000 | O13: =SUM(C13:N13)
A14: Professional Services | B14: Expenses | C14: 5000 | D14: 5000 | E14: 5000 | F14: 5000 | G14: 5000 | H14: 5000 | I14: 5000 | J14: 5000 | K14: 5000 | L14: 5000 | M14: 5000 | N14: 5000 | O14: =SUM(C14:N14)
A15: R&D / Training | B15: Expenses | C15: 3500 | D15: 3500 | E15: 3500 | F15: 3500 | G15: 3500 | H15: 3500 | I15: 3500 | J15: 3500 | K15: 3500 | L15: 3500 | M15: 3500 | N15: 3500 | O15: =SUM(C15:N15)
A16: Miscellaneous | B16: Expenses | C16: 1500 | D16: 1500 | E16: 1500 | F16: 1500 | G16: 1500 | H16: 1500 | I16: 1500 | J16: 1500 | K16: 1500 | L16: 1500 | M16: 1500 | N16: 1500 | O16: =SUM(C16:N16)

Sheet 📈 Variance Analysis
A1: BUDGET vs ACTUAL VARIANCE ANALYSIS | 2026 | Full Item-by-Item Breakdown
B2: Line Item | C2: Budgeted (Annual) | D2: Actual (Annual) | E2: $ Variance | F2: % Variance | G2: Q1 Budget | H2: Q1 Actual | I2: Q2 Budget | J2: Q2 Actual | K2: Q3 Budget | L2: Q3 Actual | M2: Status
A3: ── REVENUE ──
B4: Product Sales | C4: =SUM('🎯 Budget Targets'!C4:N4) | D4: ='💰 Budget Data'!O4 | E4: =D4-C4 | F4: =IFERROR(E4/ABS(C4),0) | G4: =SUM('🎯 Budget Targets'!C4:E4) | H4: =SUM('💰 Budget Data'!C4:E4) | I4: =SUM('🎯 Budget Targets'!F4:H4) | J4: =SUM('💰 Budget Data'!F4:H4) | K4: =SUM('🎯 Budget Targets'!I4:K4) | L4: =SUM('💰 Budget Data'!I4:K4) | M4: =IF(D4>=C4,"✅ On Target",IF(ABS(F4)<0.1,"⚠️ Near Target","❌ Off Target"))
B5: Service Revenue | C5: =SUM('🎯 Budget Targets'!C5:N5) | D5: ='💰 Budget Data'!O5 | E5: =D5-C5 | F5: =IFERROR(E5/ABS(C5),0) | G5: =SUM('🎯 Budget Targets'!C5:E5) | H5: =SUM('💰 Budget Data'!C5:E5) | I5: =SUM('🎯 Budget Targets'!F5:H5) | J5: =SUM('💰 Budget Data'!F5:H5) | K5: =SUM('🎯 Budget Targets'!I5:K5) | L5: =SUM('💰 Budget Data'!I5:K5) | M5: =IF(D5>=C5,"✅ On Target",IF(ABS(F5)<0.1,"⚠️ Near Target","❌ Off Target"))
B6: Other Income | C6: =SUM('🎯 Budget Targets'!C6:N6) | D6: ='💰 Budget Data'!O6 | E6: =D6-C6 | F6: =IFERROR(E6/ABS(C6),0) | G6: =SUM('🎯 Budget Targets'!C6:E6) | H6: =SUM('💰 Budget Data'!C6:E6) | I6: =SUM('🎯 Budget Targets'!F6:H6) | J6: =SUM('💰 Budget Data'!F6:H6) | K6: =SUM('🎯 Budget Targets'!I6:K6) | L6: =SUM('💰 Budget Data'!I6:K6) | M6: =IF(D6>=C6,"✅ On Target",IF(ABS(F6)<0.1,"⚠️ Near Target","❌ Off Target"))
B7: TOTAL REVENUE | C7: =SUM('🎯 Budget Targets'!C4:N4)+SUM('🎯 Budget Targets'!C5:N5)+SUM('🎯 Budget Targets'!C6:N6) | D7: ='💰 Budget Data'!O17 | E7: =D7-C7 | F7: =IFERROR(E7/ABS(C7),0) | G7: =SUM('🎯 Budget Targets'!C4:E4)+SUM('🎯 Budget Targets'!C5:E5)+SUM('🎯 Budget Targets'!C6:E6) | H7: =SUM('💰 Budget Data'!C17:E17) | I7: =SUM('🎯 Budget Targets'!F4:H4)+SUM('🎯 Budget Targets'!F5:H5)+SUM('🎯 Budget Targets'!F6:H6) | J7: =SUM('💰 Budget Data'!F17:H17) | K7: =SUM('🎯 Budget Targets'!I4:K4)+SUM('🎯 Budget Targets'!I5:K5)+SUM('🎯 Budget Targets'!I6:K6) | L7: =SUM('💰 Budget Data'!I17:K17) | M7: =IF(D7>=C7,"✅ On Target",IF(ABS(F7)<0.1,"⚠️ Near Target","❌ Off Target"))
A8: ── EXPENSES ──
B9: Salaries & Wages | C9: =SUM('🎯 Budget Targets'!C9:N9) | D9: ='💰 Budget Data'!O8 | E9: =D9-C9 | F9: =IFERROR(E9/ABS(C9),0) | G9: =SUM('🎯 Budget Targets'!C9:E9) | H9: =SUM('💰 Budget Data'!C8:E8) | I9: =SUM('🎯 Budget Targets'!F9:H9) | J9: =SUM('💰 Budget Data'!F8:H8) | K9: =SUM('🎯 Budget Targets'!I9:K9) | L9: =SUM('💰 Budget Data'!I8:K8) | M9: =IF(D9>=C9,"✅ On Target",IF(ABS(F9)<0.1,"⚠️ Near Target","❌ Off Target"))
B10: Rent & Utilities | C10: =SUM('🎯 Budget Targets'!C10:N10) | D10: ='💰 Budget Data'!O9 | E10: =D10-C10 | F10: =IFERROR(E10/ABS(C10),0) | G10: =SUM('🎯 Budget Targets'!C10:E10) | H10: =SUM('💰 Budget Data'!C9:E9) | I10: =SUM('🎯 Budget Targets'!F10:H10) | J10: =SUM('💰 Budget Data'!F9:H9) | K10: =SUM('🎯 Budget Targets'!I10:K10) | L10: =SUM('💰 Budget Data'!I9:K9) | M10: =IF(D10>=C10,"✅ On Target",IF(ABS(F10)<0.1,"⚠️ Near Target","❌ Off Target"))
B11: Marketing & Ads | C11: =SUM('🎯 Budget Targets'!C11:N11) | D11: ='💰 Budget Data'!O10 | E11: =D11-C11 | F11: =IFERROR(E11/ABS(C11),0) | G11: =SUM('🎯 Budget Targets'!C11:E11) | H11: =SUM('💰 Budget Data'!C10:E10) | I11: =SUM('🎯 Budget Targets'!F11:H11) | J11: =SUM('💰 Budget Data'!F10:H10) | K11: =SUM('🎯 Budget Targets'!I11:K11) | L11: =SUM('💰 Budget Data'!I10:K10) | M11: =IF(D11>=C11,"✅ On Target",IF(ABS(F11)<0.1,"⚠️ Near Target","❌ Off Target"))
B12: Software & Tools | C12: =SUM('🎯 Budget Targets'!C12:N12) | D12: ='💰 Budget Data'!O11 | E12: =D12-C12 | F12: =IFERROR(E12/ABS(C12),0) | G12: =SUM('🎯 Budget Targets'!C12:E12) | H12: =SUM('💰 Budget Data'!C11:E11) | I12: =SUM('🎯 Budget Targets'!F12:H12) | J12: =SUM('💰 Budget Data'!F11:H11) | K12: =SUM('🎯 Budget Targets'!I12:K12) | L12: =SUM('💰 Budget Data'!I11:K11) | M12: =IF(D12>=C12,"✅ On Target",IF(ABS(F12)<0.1,"⚠️ Near Target","❌ Off Target"))
B13: Travel & Entertainment | C13: =SUM('🎯 Budget Targets'!C13:N13) | D13: ='💰 Budget Data'!O12 | E13: =D13-C13 | F13: =IFERROR(E13/ABS(C13),0) | G13: =SUM('🎯 Budget Targets'!C13:E13) | H13: =SUM('💰 Budget Data'!C12:E12) | I13: =SUM('🎯 Budget Targets'!F13:H13) | J13: =SUM('💰 Budget Data'!F12:H12) | K13: =SUM('🎯 Budget Targets'!I13:K13) | L13: =SUM('💰 Budget Data'!I12:K12) | M13: =IF(D13>=C13,"✅ On Target",IF(ABS(F13)<0.1,"⚠️ Near Target","❌ Off Target"))
B14: Office Supplies | C14: =SUM('🎯 Budget Targets'!C14:N14) | D14: ='💰 Budget Data'!O13 | E14: =D14-C14 | F14: =IFERROR(E14/ABS(C14),0) | G14: =SUM('🎯 Budget Targets'!C14:E14) | H14: =SUM('💰 Budget Data'!C13:E13) | I14: =SUM('🎯 Budget Targets'!F14:H14) | J14: =SUM('💰 Budget Data'!F13:H13) | K14: =SUM('🎯 Budget Targets'!I14:K14) | L14: =SUM('💰 Budget Data'!I13:K13) | M14: =IF(D14>=C14,"✅ On Target",IF(ABS(F14)<0.1,"⚠️ Near Target","❌ Off Target"))
B15: Professional Services | C15: =SUM('🎯 Budget Targets'!C15:N15) | D15: ='💰 Budget Data'!O14 | E15: =D15-C15 | F15: =IFERROR(E15/ABS(C15),0) | G15: =SUM('🎯 Budget Targets'!C15:E15) | H15: =SUM('💰 Budget Data'!C14:E14) | I15: =SUM('🎯 Budget Targets'!F15:H15) | J15: =SUM('💰 Budget Data'!F14:H14) | K15: =SUM('🎯 Budget Targets'!I15:K15) | L15: =SUM('💰 Budget Data'!I14:K14) | M15: =IF(D15>=C15,"✅ On Target",IF(ABS(F15)<0.1,"⚠️ Near Target","❌ Off Target"))
B16: R&D / Training | C16: =SUM('🎯 Budget Targets'!C16:N16) | D16: ='💰 Budget Data'!O15 | E16: =D16-C16 | F16: =IFERROR(E16/ABS(C16),0) | G16: =SUM('🎯 Budget Targets'!C16:E16) | H16: =SUM('💰 Budget Data'!C15:E15) | I16: =SUM('🎯 Budget Targets'!F16:H16) | J16: =SUM('💰 Budget Data'!F15:H15) | K16: =SUM('🎯 Budget Targets'!I16:K16) | L16: =SUM('💰 Budget Data'!I15:K15) | M16: =IF(D16>=C16,"✅ On Target",IF(ABS(F16)<0.1,"⚠️ Near Target","❌ Off Target"))
B17: Miscellaneous | C17: =SUM('🎯 Budget Targets'!C17:N17) | D17: ='💰 Budget Data'!O16 | E17: =D17-C17 | F17: =IFERROR(E17/ABS(C17),0) | G17: =SUM('🎯 Budget Targets'!C17:E17) | H17: =SUM('💰 Budget Data'!C16:E16) | I17: =SUM('🎯 Budget Targets'!F17:H17) | J17: =SUM('💰 Budget Data'!F16:H16) | K17: =SUM('🎯 Budget Targets'!I17:K17) | L17: =SUM('💰 Budget Data'!I16:K16) | M17: =IF(D17>=C17,"✅ On Target",IF(ABS(F17)<0.1,"⚠️ Near Target","❌ Off Target"))
B18: TOTAL EXPENSES | C18: =SUM('🎯 Budget Targets'!C9:N9)+SUM('🎯 Budget Targets'!C10:N10)+SUM('🎯 Budget Targets'!C11:N11)+SUM('🎯 Budget Targets'!C12:N12)+SUM('🎯 Budget Targets'!C13:N13)+SUM('🎯 Budget Targets'!C14:N14)+SUM('🎯 Budget Targets'!C15:N15)+SUM('🎯 Budget Targets'!C16:N16)+SUM('🎯 Budget Targets'!C17:N17) | D18: ='💰 Budget Data'!O18 | E18: =D18-C18 | F18: =IFERROR(E18/ABS(C18),0) | G18: =SUM('🎯 Budget Targets'!C9:E9)+SUM('🎯 Budget Targets'!C10:E10)+SUM('🎯 Budget Targets'!C11:E11)+SUM('🎯 Budget Targets'!C12:E12)+SUM('🎯 Budget Targets'!C13:E13)+SUM('🎯 Budget Targets'!C14:E14)+SUM('🎯 Budget Targets'!C15:E15)+SUM('🎯 Budget Targets'!C16:E16)+SUM('🎯 Budget Targets'!C17:E17) | H18: =SUM('💰 Budget Data'!C18:E18) | I18: =SUM('🎯 Budget Targets'!F9:H9)+SUM('🎯 Budget Targets'!F10:H10)+SUM('🎯 Budget Targets'!F11:H11)+SUM('🎯 Budget Targets'!F12:H12)+SUM('🎯 Budget Targets'!F13:H13)+SUM('🎯 Budget Targets'!F14:H14)+SUM('🎯 Budget Targets'!F15:H15)+SUM('🎯 Budget Targets'!F16:H16)+SUM('🎯 Budget Targets'!F17:H17) | J18: =SUM('💰 Budget Data'!F18:H18) | K18: =SUM('🎯 Budget Targets'!I9:K9)+SUM('🎯 Budget Targets'!I10:K10)+SUM('🎯 Budget Targets'!I11:K11)+SUM('🎯 Budget Targets'!I12:K12)+SUM('🎯 Budget Targets'!I13:K13)+SUM('🎯 Budget Targets'!I14:K14)+SUM('🎯 Budget Targets'!I15:K15)+SUM('🎯 Budget Targets'!I16:K16)+SUM('🎯 Budget Targets'!I17:K17) | L18: =SUM('💰 Budget Data'!I18:K18) | M18: =IF(D18>=C18,"✅ On Target",IF(ABS(F18)<0.1,"⚠️ Near Target","❌ Off Target"))
B19: NET PROFIT | C19: =C9-C18 | D19: ='💰 Budget Data'!O19 | E19: =D19-C19 | F19: =IFERROR(E19/ABS(C19),0) | G19: =G9-G18 | H19: =SUM('💰 Budget Data'!C19:E19) | I19: =I9-I18 | J19: =SUM('💰 Budget Data'!F19:H19) | K19: =K9-K18 | L19: =SUM('💰 Budget Data'!I19:K19) | M19: =IF(D19>=C19,"✅ On Target",IF(ABS(F19)<0.1,"⚠️ Near Target","❌ Off Target"))

Sheet 📋 Executive Summary
A1: EXECUTIVE BUDGET SUMMARY | 2026
A3: KEY FINANCIAL METRICS
B4: Total Revenue (Actual) | C4: ='💰 Budget Data'!O17 | D4: vs Budget: compare row 3 of Variance
B5: Total Revenue (Budget) | C5: =SUM('🎯 Budget Targets'!C4:N4)+SUM('🎯 Budget Targets'!C5:N5)+SUM('🎯 Budget Targets'!C6:N6)
B6: Total Expenses (Actual) | C6: ='💰 Budget Data'!O18
B7: Net Profit (Actual) | C7: ='💰 Budget Data'!O19
B8: Net Profit Margin | C8: =IFERROR('💰 Budget Data'!O19/'💰 Budget Data'!O17,0)
B9: Best Revenue Month | C9: =INDEX({"Jan","Feb","Mar","Apr","May","Jun","Jul","Aug","Sep","Oct","Nov","Dec"},MATCH(MAX('💰 Budget Data'!C17:N17),'💰 Budget Data'!C17:N17,0))
B10: Highest Expense Month | C10: =INDEX({"Jan","Feb","Mar","Apr","May","Jun","Jul","Aug","Sep","Oct","Nov","Dec"},MATCH(MAX('💰 Budget Data'!C18:N18),'💰 Budget Data'!C18:N18,0))
B11: Avg Monthly Net Profit | C11: =AVERAGE('💰 Budget Data'!C19:N19)
A15: Prepared by Farhan Siddique | Digital Marketer & Data Analyst | HubSpot, Google & Microsoft Certified
A16: Available on Fiverr & Upwork | Excel Dashboards • SEO Audits • Email Marketing
